odoo/addons/report_alternative_layout/README.rst
odoo/addons/report_alternative_layout/__init__.py
odoo/addons/report_alternative_layout/__manifest__.py
odoo/addons/report_alternative_layout/data/report_paperformat_data.xml
odoo/addons/report_alternative_layout/i18n/ja.po
odoo/addons/report_alternative_layout/i18n/report_alternative_layout.pot
odoo/addons/report_alternative_layout/models/__init__.py
odoo/addons/report_alternative_layout/models/ir_actions_report.py
odoo/addons/report_alternative_layout/models/report_paperformat.py
odoo/addons/report_alternative_layout/readme/CONFIGURE.md
odoo/addons/report_alternative_layout/readme/CONTRIBUTORS.md
odoo/addons/report_alternative_layout/readme/DESCRIPTION.md
odoo/addons/report_alternative_layout/report/report_template.xml
odoo/addons/report_alternative_layout/static/description/icon.png
odoo/addons/report_alternative_layout/static/description/index.html
odoo/addons/report_alternative_layout/views/ir_actions_report_views.xml
odoo/addons/report_alternative_layout/views/report_paperformat_views.xml
odoo_addon_report_alternative_layout-18.0.1.1.0.dist-info/METADATA
odoo_addon_report_alternative_layout-18.0.1.1.0.dist-info/WHEEL
odoo_addon_report_alternative_layout-18.0.1.1.0.dist-info/top_level.txt
odoo_addon_report_alternative_layout-18.0.1.1.0.dist-info/RECORD
